{
    "wikipedia": "https://wikipedia.org/wiki/May_5",
    "date": "May 5",
    "births": [
        {
            "year": "1210",
            "description": "Afonso III of Portugal (d. 1279)",
            "wikipedia": [
                {
                    "title": "Afonso III of Portugal",
                    "wikipedia": "https://wikipedia.org/wiki/Afonso_III_of_Portugal"
                }
            ],
            "url_image": "https://upload.wikimedia.org/wikipedia/commons/thumb/0/0e/Dom_Afonso_III.jpg/1200px-Dom_Afonso_III.jpg"
        },
        {
            "year": "1282",
            "description": "Juan Manuel, Prince of Villena (d. 1322)",
            "wikipedia": [
                {
                    "title": "Juan Manuel, Prince of Villena",
                    "wikipedia": "https://wikipedia.org/wiki/Juan_Manuel,_Prince_of_Villena"
                }
            ],
            "url_image": "https://upload.wikimedia.org/wikipedia/commons/0/06/Don_Juan_Manuel.jpg"
        },
        {
            "year": "1310",
            "description": "Preczlaw of Pogarell, Cardinal and Bishop of Wrocław (d. 1376)",
            "wikipedia": [
                {
                    "title": "Preczlaw of Pogarell",
                    "wikipedia": "https://wikipedia.org/wiki/Preczlaw_of_Pogarell"
                },
                {
                    "title": "Cardinal (Catholicism)",
                    "wikipedia": "https://wikipedia.org/wiki/Cardinal_(Catholicism)"
                },
                {
                    "title": "Bishop of Wrocław",
                    "wikipedia": "https://wikipedia.org/wiki/Bishop_of_Wroc%C5%82aw"
                }
            ],
            "url_image": "https://upload.wikimedia.org/wikipedia/commons/thumb/5/58/Przec%C5%82aw_z_Pogorzeli.jpg/1200px-Przec%C5%82aw_z_Pogorzeli.jpg"
        },
        {
            "year": "1352",
            "description": "Rupert of Germany, Count Palatine of the Rhine (d. 1410)",
            "wikipedia": [
                {
                    "title": "Rupert of Germany",
                    "wikipedia": "https://wikipedia.org/wiki/Rupert_of_Germany"
                }
            ],
            "url_image": "https://upload.wikimedia.org/wikipedia/commons/0/00/Rupprecht_III._von_der_Pfalz.jpg"
        },
        {
            "year": "1479",
            "description": "Guru Amar Das, Indian 3rd Sikh Guru (d. 1574)",
            "wikipedia": [
                {
                    "title": "Guru Amar Das",
                    "wikipedia": "https://wikipedia.org/wiki/Guru_Amar_Das"
                },
                {
                    "title": "Sikh Guru",
                    "wikipedia": "https://wikipedia.org/wiki/Sikh_Guru"
                }
            ],
            "url_image": "https://sikhsewak.files.wordpress.com/2015/06/guru-amar-das.jpg"
        },
        {
            "year": "1504",
            "description": "Stanislaus Hosius, Polish cardinal (d. 1579)",
            "wikipedia": [
                {
                    "title": "Stanislaus Hosius",
                    "wikipedia": "https://wikipedia.org/wiki/Stanislaus_Hosius"
                }
            ],
            "url_image": "https://upload.wikimedia.org/wikipedia/commons/5/5c/Stanis%C5%82aw_Hozjusz_1.PNG"
        },
        {
            "year": "1530",
            "description": "Gabriel, comte de Montgomery, French nobleman (d. 1574)",
            "wikipedia": [
                {
                    "title": "Gabriel, comte de Montgomery",
                    "wikipedia": "https://wikipedia.org/wiki/Gabriel,_comte_de_Montgomery"
                }
            ],
            "url_image": "https://upload.wikimedia.org/wikipedia/commons/d/d0/Gabriel_de_Lorges_comte_de_Montgomery_1530_1574_by_Feron_Eloi_Firmin.jpg"
        },
        {
            "year": "1542",
            "description": "Thomas Cecil, 1st Earl of Exeter, English soldier and politician, Lord Lieutenant of Northamptonshire (d. 1623)",
            "wikipedia": [
                {
                    "title": "Thomas Cecil, 1st Earl of Exeter",
                    "wikipedia": "https://wikipedia.org/wiki/Thomas_Cecil,_1st_Earl_of_Exeter"
                },
                {
                    "title": "Lord Lieutenant of Northamptonshire",
                    "wikipedia": "https://wikipedia.org/wiki/Lord_Lieutenant_of_Northamptonshire"
                }
            ],
            "url_image": "https://upload.wikimedia.org/wikipedia/commons/1/15/Thomas_Cecil%2C_1st_Earl_of_Exeter_from_NPG.jpg"
        },
        {
            "year": "1582",
            "description": "John Frederick, Duke of Württemberg (1608-1628) (d. 1628)",
            "wikipedia": [
                {
                    "title": "John Frederick, Duke of Württemberg",
                    "wikipedia": "https://wikipedia.org/wiki/John_Frederick,_Duke_of_W%C3%BCrttemberg"
                }
            ],
            "url_image": "https://upload.wikimedia.org/wikipedia/commons/thumb/0/02/900-185_Herzog_Johann_Friedrich.jpg/220px-900-185_Herzog_Johann_Friedrich.jpg"
        },
        {
            "year": "1684",
            "description": "Françoise Charlotte d'Aubigné, French wife of Adrien Maurice de Noailles (d. 1739)",
            "wikipedia": [
                {
                    "title": "Françoise Charlotte d'Aubigné",
                    "wikipedia": "https://wikipedia.org/wiki/Fran%C3%A7oise_Charlotte_d%27Aubign%C3%A9"
                },
                {
                    "title": "Adrien Maurice de Noailles",
                    "wikipedia": "https://wikipedia.org/wiki/Adrien_Maurice_de_Noailles"
                }
            ],
            "url_image": "https://upload.wikimedia.org/wikipedia/commons/b/bc/Portrait_of_Fran%C3%A7oise_Charlotte_d%27Aubign%C3%A9%2C_Duchess_of_Noailles_holding_a_portrait_of_her_aunt_Madame_de_Maintenon_by_a_member_of_the_workshop_of_Nicolas_de_Largilli%C3%A8re.png"
        },
        {
            "year": "1747",
            "description": "Leopold II, Holy Roman Emperor (d. 1792)",
            "wikipedia": [
                {
                    "title": "Leopold II, Holy Roman Emperor",
                    "wikipedia": "https://wikipedia.org/wiki/Leopold_II,_Holy_Roman_Emperor"
                }
            ],
            "url_image": "https://upload.wikimedia.org/wikipedia/commons/1/1a/Leopold_II%2C_Holy_Roman_Emperor.jpg"
        },
        {
            "year": "1749",
            "description": "Jean-Frédéric Edelmann, French pianist and composer (d. 1794)",
            "wikipedia": [
                {
                    "title": "Jean-Frédéric Edelmann",
                    "wikipedia": "https://wikipedia.org/wiki/Jean-Fr%C3%A9d%C3%A9ric_Edelmann"
                }
            ],
            "url_image": "http://1.bp.blogspot.com/-mlL5XrTKCBY/T34o9zcMP-I/AAAAAAAAAD8/FeMiB9FpoYo/s1600/71370656.jpg"
        },
        {
            "year": "1764",
            "description": "Robert Craufurd, Scottish general and politician (d. 1812)",
            "wikipedia": [
                {
                    "title": "Robert Craufurd",
                    "wikipedia": "https://wikipedia.org/wiki/Robert_Craufurd"
                }
            ],
            "url_image": "https://upload.wikimedia.org/wikipedia/commons/4/4f/Mayor_general_robert_craufurd.jpg"
        },
        {
            "year": "1800",
            "description": "Louis Christophe François Hachette, French publisher (d. 1864)",
            "wikipedia": [
                {
                    "title": "Louis Christophe François Hachette",
                    "wikipedia": "https://wikipedia.org/wiki/Louis_Christophe_Fran%C3%A7ois_Hachette"
                }
            ],
            "url_image": "https://upload.wikimedia.org/wikipedia/commons/1/12/Louis_Hachette_1854.jpg"
        },
        {
            "year": "1813",
            "description": "Søren Kierkegaard, Danish philosopher and author (d. 1855)",
            "wikipedia": [
                {
                    "title": "Søren Kierkegaard",
                    "wikipedia": "https://wikipedia.org/wiki/S%C3%B8ren_Kierkegaard"
                }
            ],
            "url_image": "https://upload.wikimedia.org/wikipedia/commons/d/d4/S%C3%B8ren_Kierkegaard_%281813-1855%29_-_%28cropped%29.jpg"
        },
        {
            "year": "1818",
            "description": "Karl Marx, German philosopher, sociologist, and journalist (d. 1883)",
            "wikipedia": [
                {
                    "title": "Karl Marx",
                    "wikipedia": "https://wikipedia.org/wiki/Karl_Marx"
                }
            ],
            "url_image": "https://upload.wikimedia.org/wikipedia/commons/thumb/d/d4/Karl_Marx_001.jpg/1200px-Karl_Marx_001.jpg"
        },
        {
            "year": "1826",
            "description": "Eugénie de Montijo, French wife of Napoleon III (d. 1920)",
            "wikipedia": [
                {
                    "title": "Eugénie de Montijo",
                    "wikipedia": "https://wikipedia.org/wiki/Eug%C3%A9nie_de_Montijo"
                },
                {
                    "title": "Napoleon III",
                    "wikipedia": "https://wikipedia.org/wiki/Napoleon_III"
                }
            ],
            "url_image": "https://upload.wikimedia.org/wikipedia/commons/d/d7/Empress_Eug%C3%A9nie_in_Court_Dress_%28after_Winterhalter%2C_Compi%C3%A8gne_IMP25%29.jpg"
        },
        {
            "year": "1830",
            "description": "John Batterson Stetson, American businessman, founded the John B. Stetson Company (d. 1906)",
            "wikipedia": [
                {
                    "title": "John Batterson Stetson",
                    "wikipedia": "https://wikipedia.org/wiki/John_Batterson_Stetson"
                },
                {
                    "title": "John B. Stetson Company",
                    "wikipedia": "https://wikipedia.org/wiki/John_B._Stetson_Company"
                }
            ],
            "url_image": "https://upload.wikimedia.org/wikipedia/commons/9/9d/StetsonPortrait.jpg"
        },
        {
            "year": "1832",
            "description": "Hubert Howe Bancroft, American ethnologist and historian (d. 1918)",
            "wikipedia": [
                {
                    "title": "Hubert Howe Bancroft",
                    "wikipedia": "https://wikipedia.org/wiki/Hubert_Howe_Bancroft"
                }
            ],
            "url_image": "https://upload.wikimedia.org/wikipedia/commons/6/6b/Hubert_Howe_Bancroft.jpg"
        },
        {
            "year": "1833",
            "description": "Ferdinand von Richthofen, German geographer and academic (d. 1905)",
            "wikipedia": [
                {
                    "title": "Ferdinand von Richthofen",
                    "wikipedia": "https://wikipedia.org/wiki/Ferdinand_von_Richthofen"
                }
            ],
            "url_image": "https://upload.wikimedia.org/wikipedia/commons/c/ce/Ferdinand_von_Richthofen.jpg"
        },
        {
            "year": "1834",
            "description": "Viktor Hartmann, Russian painter and architect (d. 1873)",
            "wikipedia": [
                {
                    "title": "Viktor Hartmann",
                    "wikipedia": "https://wikipedia.org/wiki/Viktor_Hartmann"
                }
            ],
            "url_image": "https://upload.wikimedia.org/wikipedia/commons/thumb/e/ea/Viktor_Gartman.jpg/200px-Viktor_Gartman.jpg"
        },
        {
            "year": "1843",
            "description": "William George Beers, Canadian dentist and patriot (d. 1900)",
            "wikipedia": [
                {
                    "title": "William George Beers",
                    "wikipedia": "https://wikipedia.org/wiki/William_George_Beers"
                }
            ],
            "url_image": "https://upload.wikimedia.org/wikipedia/commons/c/cf/WilliamGeorgeBeers.JPG"
        },
        {
            "year": "1846",
            "description": "Henryk Sienkiewicz, Polish journalist and author, Nobel Prize laureate (d. 1916)",
            "wikipedia": [
                {
                    "title": "Henryk Sienkiewicz",
                    "wikipedia": "https://wikipedia.org/wiki/Henryk_Sienkiewicz"
                },
                {
                    "title": "Nobel Prize in Literature",
                    "wikipedia": "https://wikipedia.org/wiki/Nobel_Prize_in_Literature"
                }
            ],
            "url_image": "https://upload.wikimedia.org/wikipedia/commons/thumb/9/9e/Stanis%C5%82aw_Biza%C5%84ski-H.Sienkiewicz.jpg/200px-Stanis%C5%82aw_Biza%C5%84ski-H.Sienkiewicz.jpg"
        },
        {
            "year": "1858",
            "description": "John L. Leal, American physician (d. 1914)",
            "wikipedia": [
                {
                    "title": "John L. Leal",
                    "wikipedia": "https://wikipedia.org/wiki/John_L._Leal"
                }
            ],
            "url_image": "https://upload.wikimedia.org/wikipedia/commons/9/92/Dr._John_L._Leal.JPG"
        },
        {
            "year": "1864",
            "description": "Nellie Bly, American journalist and author (d. 1922)",
            "wikipedia": [
                {
                    "title": "Nellie Bly",
                    "wikipedia": "https://wikipedia.org/wiki/Nellie_Bly"
                }
            ],
            "url_image": "https://upload.wikimedia.org/wikipedia/commons/5/52/Nellie_Bly_2.jpg"
        },
        {
            "year": "1865",
            "description": "Helen Maud Merrill, American litterateur and poet (d. 1943)",
            "wikipedia": [
                {
                    "title": "Helen Maud Merrill",
                    "wikipedia": "https://wikipedia.org/wiki/Helen_Maud_Merrill"
                }
            ],
            "url_image": "https://upload.wikimedia.org/wikipedia/commons/thumb/f/f2/Helen_Maud_Merrill.png/220px-Helen_Maud_Merrill.png"
        },
        {
            "year": "1866",
            "description": "Thomas B. Thrige, Danish businessman (d. 1938)",
            "wikipedia": [
                {
                    "title": "Thomas B. Thrige",
                    "wikipedia": "https://wikipedia.org/wiki/Thomas_B._Thrige"
                }
            ],
            "url_image": "https://odenseleksikon.files.wordpress.com/2020/05/b0011026d.jpg?w=558"
        },
        {
            "year": "1869",
            "description": "Fabián de la Rosa, Filipino painter and educator (d. 1937)",
            "wikipedia": [
                {
                    "title": "Fabián de la Rosa",
                    "wikipedia": "https://wikipedia.org/wiki/Fabi%C3%A1n_de_la_Rosa"
                }
            ],
            "url_image": "https://i.pinimg.com/originals/b0/3b/d6/b03bd6000d03627f513bffd36cbabb1b.jpg"
        },
        {
            "year": "1869",
            "description": "Hans Pfitzner, German composer and conductor (d. 1949)",
            "wikipedia": [
                {
                    "title": "Hans Pfitzner",
                    "wikipedia": "https://wikipedia.org/wiki/Hans_Pfitzner"
                }
            ],
            "url_image": "https://upload.wikimedia.org/wikipedia/commons/d/d1/Hans_Pfitzner_by_Wanda_von_Debschitz-Kunowski%2C_ca_1910.jpg"
        },
        {
            "year": "1874",
            "description": "Thomas Bavin, New Zealand-Australian politician, 24th Premier of New South Wales (d. 1941)",
            "wikipedia": [
                {
                    "title": "Thomas Bavin",
                    "wikipedia": "https://wikipedia.org/wiki/Thomas_Bavin"
                },
                {
                    "title": "Premier of New South Wales",
                    "wikipedia": "https://wikipedia.org/wiki/Premier_of_New_South_Wales"
                }
            ],
            "url_image": "https://upload.wikimedia.org/wikipedia/commons/9/91/Tom_Bavin_1932_%28cropped%29.jpg"
        },
        {
            "year": "1883",
            "description": "Archibald Wavell, 1st Earl Wavell, English general and politician, 43rd Governor-General of India (d. 1950)",
            "wikipedia": [
                {
                    "title": "Archibald Wavell, 1st Earl Wavell",
                    "wikipedia": "https://wikipedia.org/wiki/Archibald_Wavell,_1st_Earl_Wavell"
                },
                {
                    "title": "Governor-General of India",
                    "wikipedia": "https://wikipedia.org/wiki/Governor-General_of_India"
                }
            ],
            "url_image": "https://upload.wikimedia.org/wikipedia/commons/thumb/d/d5/Archibald_Wavell%2C_1st_Earl_Wavell.jpg/220px-Archibald_Wavell%2C_1st_Earl_Wavell.jpg"
        },
        {
            "year": "1884",
            "description": "Chief Bender, American baseball player and coach (d. 1954)",
            "wikipedia": [
                {
                    "title": "Chief Bender",
                    "wikipedia": "https://wikipedia.org/wiki/Chief_Bender"
                }
            ],
            "url_image": "https://upload.wikimedia.org/wikipedia/commons/0/06/Chief_Bender%2C_Philadelphia_Athletics_pitcher%2C_by_Paul_Thompson%2C_1911.jpg"
        },
        {
            "year": "1887",
            "description": "Mervyn S. Bennion, American captain, Medal of Honor recipient (d. 1941)",
            "wikipedia": [
                {
                    "title": "Mervyn S. Bennion",
                    "wikipedia": "https://wikipedia.org/wiki/Mervyn_S._Bennion"
                },
                {
                    "title": "Medal of Honor",
                    "wikipedia": "https://wikipedia.org/wiki/Medal_of_Honor"
                }
            ],
            "url_image": "https://upload.wikimedia.org/wikipedia/commons/6/67/Mervyn_Sharp_Bennion.jpg"
        },
        {
            "year": "1885",
            "description": "Kingsley Fairbridge, South African-Australian scholar and politician (d. 1924)",
            "wikipedia": [
                {
                    "title": "Kingsley Fairbridge",
                    "wikipedia": "https://wikipedia.org/wiki/Kingsley_Fairbridge"
                }
            ],
            "url_image": "https://upload.wikimedia.org/wikipedia/commons/d/d8/Kingsley_Fairbridge.JPG"
        },
        {
            "year": "1889",
            "description": "Herbie Taylor, South African cricketer and soldier (d. 1973)",
            "wikipedia": [
                {
                    "title": "Herbie Taylor",
                    "wikipedia": "https://wikipedia.org/wiki/Herbie_Taylor"
                }
            ],
            "url_image": "https://upload.wikimedia.org/wikipedia/commons/7/73/Herbie_Taylor_1924-04-29.jpg"
        },
        {
            "year": "1890",
            "description": "Christopher Morley, American journalist and author (d. 1957)",
            "wikipedia": [
                {
                    "title": "Christopher Morley",
                    "wikipedia": "https://wikipedia.org/wiki/Christopher_Morley"
                }
            ],
            "url_image": "https://upload.wikimedia.org/wikipedia/commons/thumb/6/60/Christopher_Darlington_Morley_cph.3b14371.jpg/1200px-Christopher_Darlington_Morley_cph.3b14371.jpg"
        },
        {
            "year": "1892",
            "description": "Dorothy Garrod, British archaeologist (d. 1968)",
            "wikipedia": [
                {
                    "title": "Dorothy Garrod",
                    "wikipedia": "https://wikipedia.org/wiki/Dorothy_Garrod"
                }
            ],
            "url_image": "https://upload.wikimedia.org/wikipedia/commons/f/fd/Dorothy_Garrod.jpg"
        },
        {
            "year": "1898",
            "description": "Elsie Eaves, American engineer (d. 1983)",
            "wikipedia": [
                {
                    "title": "Elsie Eaves",
                    "wikipedia": "https://wikipedia.org/wiki/Elsie_Eaves"
                }
            ],
            "url_image": "https://www.engineergirl.org/File.aspx?id=41749&v=9da5eb9"
        },
        {
            "year": "1898",
            "description": "Blind Willie McTell, American Piedmont blues singer and guitar player (d. 1959)",
            "wikipedia": [
                {
                    "title": "Blind Willie McTell",
                    "wikipedia": "https://wikipedia.org/wiki/Blind_Willie_McTell"
                }
            ],
            "url_image": "https://upload.wikimedia.org/wikipedia/commons/thumb/4/4f/Blind_Willie_McTell_LOC.jpg/200px-Blind_Willie_McTell_LOC.jpg"
        },
        {
            "year": "1899",
            "description": "Freeman Gosden, American actor and screenwriter (d. 1982)",
            "wikipedia": [
                {
                    "title": "Freeman Gosden",
                    "wikipedia": "https://wikipedia.org/wiki/Freeman_Gosden"
                }
            ],
            "url_image": "https://upload.wikimedia.org/wikipedia/commons/7/71/Charles_Correll_Freeman_Gosden_1939.JPG"
        },
        {
            "year": "1900",
            "description": "Helen Redfield, American geneticist (d. 1988) [1]",
            "wikipedia": [
                {
                    "title": "Helen Redfield",
                    "wikipedia": "https://wikipedia.org/wiki/Helen_Redfield"
                }
            ],
            "url_image": "https://upload.wikimedia.org/wikipedia/commons/6/68/Helen_Redfield_b._1900.jpg"
        },
        {
            "year": "1903",
            "description": "James Beard, American chef and author (d. 1985)",
            "wikipedia": [
                {
                    "title": "James Beard",
                    "wikipedia": "https://wikipedia.org/wiki/James_Beard"
                }
            ],
            "url_image": "https://upload.wikimedia.org/wikipedia/commons/a/ae/James_Beard.jpg"
        },
        {
            "year": "1905",
            "description": "Floyd Gottfredson, American author and illustrator (d. 1986)",
            "wikipedia": [
                {
                    "title": "Floyd Gottfredson",
                    "wikipedia": "https://wikipedia.org/wiki/Floyd_Gottfredson"
                }
            ],
            "url_image": "https://upload.wikimedia.org/wikipedia/en/thumb/7/79/Gottfredson_photo.jpg/220px-Gottfredson_photo.jpg"
        },
        {
            "year": "1906",
            "description": "Charles Exbrayat, French author and screenwriter (d. 1989)",
            "wikipedia": [
                {
                    "title": "Charles Exbrayat",
                    "wikipedia": "https://wikipedia.org/wiki/Charles_Exbrayat"
                }
            ],
            "url_image": "https://upload.wikimedia.org/wikipedia/commons/a/a1/Charles_Ebrayat%2C_vers_1940.jpg"
        },
        {
            "year": "1907",
            "description": "Iryna Vilde, Ukrainian journalist and author (d. 1982)",
            "wikipedia": [
                {
                    "title": "Iryna Vilde",
                    "wikipedia": "https://wikipedia.org/wiki/Iryna_Vilde"
                }
            ],
            "url_image": "https://upload.wikimedia.org/wikipedia/commons/c/c0/Iryna_Vilde.jpg"
        },
        {
            "year": "1908",
            "description": "Kurt Böhme, German opera singer (d. 1989)",
            "wikipedia": [
                {
                    "title": "Kurt Böhme",
                    "wikipedia": "https://wikipedia.org/wiki/Kurt_B%C3%B6hme"
                }
            ],
            "url_image": "https://upload.wikimedia.org/wikipedia/pt/6/64/Kurt_B%C3%B6hme.jpg"
        },
        {
            "year": "1909",
            "description": "Miklós Radnóti, Hungarian poet and author (d. 1944)",
            "wikipedia": [
                {
                    "title": "Miklós Radnóti",
                    "wikipedia": "https://wikipedia.org/wiki/Mikl%C3%B3s_Radn%C3%B3ti"
                }
            ],
            "url_image": "https://upload.wikimedia.org/wikipedia/commons/thumb/7/7e/Radn%C3%B3ti_Mikl%C3%B3s_%281930%29.jpg/200px-Radn%C3%B3ti_Mikl%C3%B3s_%281930%29.jpg"
        },
        {
            "year": "1910",
            "description": "Leo Lionni, American author and illustrator (d. 1999)",
            "wikipedia": [
                {
                    "title": "Leo Lionni",
                    "wikipedia": "https://wikipedia.org/wiki/Leo_Lionni"
                }
            ],
            "url_image": "https://images-na.ssl-images-amazon.com/images/I/818iB5v3+eL.jpg"
        },
        {
            "year": "1911",
            "description": "Gilles Grangier, French director and screenwriter (d. 1996)",
            "wikipedia": [
                {
                    "title": "Gilles Grangier",
                    "wikipedia": "https://wikipedia.org/wiki/Gilles_Grangier"
                }
            ],
            "url_image": "https://resize-media.festival-cannes.com/fit-in/584x794/film_film/0001/78/38c67caab5f0aab55f9b7f64567efcd63fc20f61.jpeg"
        },
        {
            "year": "1911",
            "description": "Andor Lilienthal, Russian-Hungarian chess player (d. 2010)",
            "wikipedia": [
                {
                    "title": "Andor Lilienthal",
                    "wikipedia": "https://wikipedia.org/wiki/Andor_Lilienthal"
                }
            ],
            "url_image": "https://upload.wikimedia.org/wikipedia/en/e/e1/Andor_Lilienthal_at_the_chessboard.jpg"
        },
        {
            "year": "1911",
            "description": "Pritilata Waddedar, Indian educator and activist (d. 1932)",
            "wikipedia": [
                {
                    "title": "Pritilata Waddedar",
                    "wikipedia": "https://wikipedia.org/wiki/Pritilata_Waddedar"
                }
            ],
            "url_image": "https://upload.wikimedia.org/wikipedia/commons/b/b5/Original_Archived_photo_of_Pritilata_Waddedar.jpg"
        },
        {
            "year": "1913",
            "description": "Duane Carter, American racing driver (d. 1993)",
            "wikipedia": [
                {
                    "title": "Duane Carter",
                    "wikipedia": "https://wikipedia.org/wiki/Duane_Carter"
                }
            ],
            "url_image": "https://images.findagrave.com/photos250/photos/2010/66/11706_126807777428.jpg"
        },
        {
            "year": "1914",
            "description": "Tyrone Power, American actor (d. 1958)",
            "wikipedia": [
                {
                    "title": "Tyrone Power",
                    "wikipedia": "https://wikipedia.org/wiki/Tyrone_Power"
                }
            ],
            "url_image": "https://upload.wikimedia.org/wikipedia/commons/7/73/Tyrone_Power_-_still.jpg"
        },
        {
            "year": "1915",
            "description": "Alice Faye, American actress and singer (d. 1998)",
            "wikipedia": [
                {
                    "title": "Alice Faye",
                    "wikipedia": "https://wikipedia.org/wiki/Alice_Faye"
                }
            ],
            "url_image": "https://upload.wikimedia.org/wikipedia/commons/6/6f/Alice_Faye_-_1944.jpg"
        },
        {
            "year": "1916",
            "description": "Zail Singh, Indian politician, 7th President of India (d. 1987)",
            "wikipedia": [
                {
                    "title": "Zail Singh",
                    "wikipedia": "https://wikipedia.org/wiki/Zail_Singh"
                },
                {
                    "title": "President of India",
                    "wikipedia": "https://wikipedia.org/wiki/President_of_India"
                }
            ],
            "url_image": "https://upload.wikimedia.org/wikipedia/commons/2/25/Giani_Zail_Singh_1995_stamp_of_India_%28cropped%29.png"
        },
        {
            "year": "1917",
            "description": "Pío Leyva, Cuban singer-songwriter (d. 2006)",
            "wikipedia": [
                {
                    "title": "Pío Leyva",
                    "wikipedia": "https://wikipedia.org/wiki/P%C3%ADo_Leyva"
                }
            ],
            "url_image": "https://img.discogs.com/rQPIeMTgSwOIDzhb4bFRP1_EJYs=/fit-in/300x300/filters:strip_icc():format(jpeg):mode_rgb():quality(40)/discogs-images/A-461009-1144730617.jpeg.jpg"
        },
        {
            "year": "1918",
            "description": "Egidio Galea, Maltese Roman Catholic priest (d. 2005)",
            "wikipedia": [
                {
                    "title": "Egidio Galea",
                    "wikipedia": "https://wikipedia.org/wiki/Egidio_Galea"
                }
            ],
            "url_image": "https://img.google-wiki.info/storage/big/53750047.jpg?ddfe0977ae8e4603bdd94024b966e7e7=4884013f58c44638390f466aaac2d237"
        },
        {
            "year": "1919",
            "description": "Georgios Papadopoulos, Greek colonel and politician, 169th Prime Minister of Greece (d. 1999)",
            "wikipedia": [
                {
                    "title": "Georgios Papadopoulos",
                    "wikipedia": "https://wikipedia.org/wiki/Georgios_Papadopoulos"
                },
                {
                    "title": "Prime Minister of Greece",
                    "wikipedia": "https://wikipedia.org/wiki/Prime_Minister_of_Greece"
                }
            ],
            "url_image": "https://upload.wikimedia.org/wikipedia/en/0/04/Georgios_Papadopoulos_crop.png"
        },
        {
            "year": "1921",
            "description": "Arthur Leonard Schawlow, American physicist and academic, Nobel Prize laureate (d. 1999)",
            "wikipedia": [
                {
                    "title": "Arthur Leonard Schawlow",
                    "wikipedia": "https://wikipedia.org/wiki/Arthur_Leonard_Schawlow"
                },
                {
                    "title": "Nobel Prize in Physics",
                    "wikipedia": "https://wikipedia.org/wiki/Nobel_Prize_in_Physics"
                }
            ],
            "url_image": "https://www.nobelprize.org/images/schawlow-13341-portrait-medium.jpg"
        },
        {
            "year": "1922",
            "description": "Irene Gut Opdyke, Polish nurse and humanitarian (d. 2003)",
            "wikipedia": [
                {
                    "title": "Irene Gut Opdyke",
                    "wikipedia": "https://wikipedia.org/wiki/Irene_Gut_Opdyke"
                }
            ],
            "url_image": "https://upload.wikimedia.org/wikipedia/en/thumb/8/86/Irene_Gut_Opdyke_-_In_My_Hands._Memories_of_a_Holocaust_Rescuer.jpg/220px-Irene_Gut_Opdyke_-_In_My_Hands._Memories_of_a_Holocaust_Rescuer.jpg"
        },
        {
            "year": "1923",
            "description": "William C. Campbell, American golfer (d. 2013)",
            "wikipedia": [
                {
                    "title": "William C. Campbell (golfer)",
                    "wikipedia": "https://wikipedia.org/wiki/William_C._Campbell_(golfer)"
                }
            ],
            "url_image": "https://upload.wikimedia.org/wikipedia/en/0/09/William_C._Campbell.jpg"
        },
        {
            "year": "1923",
            "description": "James Gilbert, Scottish television producer and director (d. 2016)",
            "wikipedia": [
                {
                    "title": "James Gilbert (producer)",
                    "wikipedia": "https://wikipedia.org/wiki/James_Gilbert_(producer)"
                }
            ],
            "url_image": "https://m.media-amazon.com/images/M/MV5BMjNlZDhlYzItYTUyOS00MDc0LTk4MDYtNDI3OTIwMTU4M2UzXkEyXkFqcGdeQXVyNjQ1MTAzNzc@._V1_UY1200_CR165,0,630,1200_AL_.jpg"
        },
        {
            "year": "1923",
            "description": "Richard Wollheim, English philosopher and academic (d. 2003)",
            "wikipedia": [
                {
                    "title": "Richard Wollheim",
                    "wikipedia": "https://wikipedia.org/wiki/Richard_Wollheim"
                }
            ],
            "url_image": "https://s35957.pcdn.co/wp-content/uploads/sites/2/2015/10/Screen-Shot-2015-10-06-at-5.06.25-PM.png"
        },
        {
            "year": "1925",
            "description": "Leo Ryan, American soldier, educator, and politician (d. 1978)",
            "wikipedia": [
                {
                    "title": "Leo Ryan",
                    "wikipedia": "https://wikipedia.org/wiki/Leo_Ryan"
                }
            ],
            "url_image": "https://upload.wikimedia.org/wikipedia/commons/thumb/3/30/Leo_Ryan.jpg/1200px-Leo_Ryan.jpg"
        },
        {
            "year": "1926",
            "description": "Ann B. Davis, American actress (d. 2014)",
            "wikipedia": [
                {
                    "title": "Ann B. Davis",
                    "wikipedia": "https://wikipedia.org/wiki/Ann_B._Davis"
                }
            ],
            "url_image": "https://citacoes.in/media/authors/ann-b-davis.jpeg"
        },
        {
            "year": "1927",
            "description": "Pat Carroll, American actress",
            "wikipedia": [
                {
                    "title": "Pat Carroll (actress)",
                    "wikipedia": "https://wikipedia.org/wiki/Pat_Carroll_(actress)"
                }
            ],
            "url_image": "https://upload.wikimedia.org/wikipedia/commons/f/f5/Pat_Carroll_1972.JPG"
        },
        {
            "year": "1927",
            "description": "Sylvia Fedoruk, Canadian physicist and politician, 17th Lieutenant Governor of Saskatchewan (d. 2012)",
            "wikipedia": [
                {
                    "title": "Sylvia Fedoruk",
                    "wikipedia": "https://wikipedia.org/wiki/Sylvia_Fedoruk"
                },
                {
                    "title": "Lieutenant Governor of Saskatchewan",
                    "wikipedia": "https://wikipedia.org/wiki/Lieutenant_Governor_of_Saskatchewan"
                }
            ],
            "url_image": "https://upload.wikimedia.org/wikipedia/en/thumb/8/8c/Sylvia_Fedoruk.jpg/220px-Sylvia_Fedoruk.jpg"
        },
        {
            "year": "1930",
            "description": "Hans Abramson, Swedish director, producer, and screenwriter (d. 2012)",
            "wikipedia": [
                {
                    "title": "Hans Abramson",
                    "wikipedia": "https://wikipedia.org/wiki/Hans_Abramson"
                }
            ],
            "url_image": "https://images.mubicdn.net/images/cast_member/172227/cache-540377-1588475339/image-w856.jpg?size=800x"
        },
        {
            "year": "1931",
            "description": "Greg, Belgian author and illustrator (d. 1999)",
            "wikipedia": [
                {
                    "title": "Greg (cartoonist)",
                    "wikipedia": "https://wikipedia.org/wiki/Greg_(cartoonist)"
                }
            ],
            "url_image": "http://canadianaci.ca/wp-content/uploads/2018/11/c-users-robert-documents-cartooning-illustration-404.jpeg"
        },
        {
            "year": "1932",
            "description": "Stan Goldberg, American illustrator (d. 2014)",
            "wikipedia": [
                {
                    "title": "Stan Goldberg",
                    "wikipedia": "https://wikipedia.org/wiki/Stan_Goldberg"
                }
            ],
            "url_image": "https://upload.wikimedia.org/wikipedia/commons/7/7d/StanGoldberg11.15.08ByLuigiNovi1.jpg"
        },
        {
            "year": "1932",
            "description": "Bob Said, American race car driver and bobsled racer (d. 2002)",
            "wikipedia": [
                {
                    "title": "Bob Said",
                    "wikipedia": "https://wikipedia.org/wiki/Bob_Said"
                },
                {
                    "title": "Bobsled",
                    "wikipedia": "https://wikipedia.org/wiki/Bobsled"
                }
            ],
            "url_image": "https://www.statsf1.com/pilotes/photos/said.png"
        },
        {
            "year": "1933",
            "description": "Igor Kashkarov, Russian high jumper",
            "wikipedia": [
                {
                    "title": "Igor Kashkarov",
                    "wikipedia": "https://wikipedia.org/wiki/Igor_Kashkarov"
                }
            ],
            "url_image": "https://lookaside.fbsbx.com/lookaside/crawler/media/?media_id=1735374340050988"
        },
        {
            "year": "1933",
            "description": "Collie Smith, Jamaican cricketer (d. 1959)",
            "wikipedia": [
                {
                    "title": "Collie Smith",
                    "wikipedia": "https://wikipedia.org/wiki/Collie_Smith"
                }
            ],
            "url_image": "https://upload.wikimedia.org/wikipedia/en/8/87/Collie_Smith.jpg"
        },
        {
            "year": "1934",
            "description": "Ace Cannon, American saxophonist",
            "wikipedia": [
                {
                    "title": "Ace Cannon",
                    "wikipedia": "https://wikipedia.org/wiki/Ace_Cannon"
                }
            ],
            "url_image": "https://images-na.ssl-images-amazon.com/images/I/51bETu0Rx8L._AC_SX425_.jpg"
        },
        {
            "year": "1934",
            "description": "Victor Garland, Australian accountant and politician, 26th Australian Minister for Veterans' Affairs",
            "wikipedia": [
                {
                    "title": "Victor Garland",
                    "wikipedia": "https://wikipedia.org/wiki/Victor_Garland"
                },
                {
                    "title": "Minister for Veterans' Affairs (Australia)",
                    "wikipedia": "https://wikipedia.org/wiki/Minister_for_Veterans%27_Affairs_(Australia)"
                }
            ],
            "url_image": "https://upload.wikimedia.org/wikipedia/commons/a/af/Vic_Garland_1969_%28cropped%29.jpg"
        },
        {
            "year": "1934",
            "description": "Johnnie Taylor, American vocalist (d. 2000)",
            "wikipedia": [
                {
                    "title": "Johnnie Taylor",
                    "wikipedia": "https://wikipedia.org/wiki/Johnnie_Taylor"
                }
            ],
            "url_image": "https://images-na.ssl-images-amazon.com/images/I/81bG4wJQSOL.jpg"
        },
        {
            "year": "1935",
            "description": "Bernard Pivot, French journalist, talk show host, and producer",
            "wikipedia": [
                {
                    "title": "Bernard Pivot",
                    "wikipedia": "https://wikipedia.org/wiki/Bernard_Pivot"
                }
            ],
            "url_image": "https://upload.wikimedia.org/wikipedia/commons/3/37/Bernard_Pivot.jpg"
        },
        {
            "year": "1935",
            "description": "Robert Rehme, American film producer",
            "wikipedia": [
                {
                    "title": "Robert Rehme",
                    "wikipedia": "https://wikipedia.org/wiki/Robert_Rehme"
                }
            ],
            "url_image": "https://media.gettyimages.com/photos/robert-rehme-wife-during-opening-night-of-the-13th-annual-afi-film-picture-id106698128?s=612x612"
        },
        {
            "year": "1936",
            "description": "Sandy Baron, American actor and comedian (d. 2001)",
            "wikipedia": [
                {
                    "title": "Sandy Baron",
                    "wikipedia": "https://wikipedia.org/wiki/Sandy_Baron"
                }
            ],
            "url_image": "https://upload.wikimedia.org/wikipedia/commons/5/59/Sandy_Baron_1968.JPG"
        },
        {
            "year": "1936",
            "description": "Patrick Gowers, English composer and educator (d. 2014)",
            "wikipedia": [
                {
                    "title": "Patrick Gowers",
                    "wikipedia": "https://wikipedia.org/wiki/Patrick_Gowers"
                }
            ],
            "url_image": "https://i.guim.co.uk/img/static/sys-images/Guardian/About/General/2015/1/28/1422463402348/Patrick-Gowers-composer-w-012.jpg?width=1200&height=630&quality=85&auto=format&fit=crop&overlay-align=bottom%2Cleft&overlay-width=100p&overlay-base64=L2ltZy9zdGF0aWMvb3ZlcmxheXMvdGctZGVmYXVsdC5wbmc&enable=upscale&s=6b891b2e1cbc41f20a285b10595562c2"
        },
        {
            "year": "1936",
            "description": "Ervin Lázár, Hungarian author (d. 2006)",
            "wikipedia": [
                {
                    "title": "Ervin Lázár",
                    "wikipedia": "https://wikipedia.org/wiki/Ervin_L%C3%A1z%C3%A1r"
                }
            ],
            "url_image": "https://upload.wikimedia.org/wikipedia/commons/9/97/Lazar_Ervin.jpg"
        },
        {
            "year": "1936",
            "description": "John Maxton, Scottish politician",
            "wikipedia": [
                {
                    "title": "John Maxton",
                    "wikipedia": "https://wikipedia.org/wiki/John_Maxton"
                }
            ],
            "url_image": "https://upload.wikimedia.org/wikipedia/commons/b/b8/Official_portrait_of_Lord_Maxton_crop_2%2C_2019.jpg"
        },
        {
            "year": "1937",
            "description": "Delia Derbyshire, English keyboard player and composer (d. 2001)",
            "wikipedia": [
                {
                    "title": "Delia Derbyshire",
                    "wikipedia": "https://wikipedia.org/wiki/Delia_Derbyshire"
                }
            ],
            "url_image": "https://ichef.bbci.co.uk/images/ic/1920x1080/p06vyw09.jpg"
        },
        {
            "year": "1938",
            "description": "Michael Murphy, American actor",
            "wikipedia": [
                {
                    "title": "Michael Murphy (actor)",
                    "wikipedia": "https://wikipedia.org/wiki/Michael_Murphy_(actor)"
                }
            ],
            "url_image": "https://upload.wikimedia.org/wikipedia/commons/9/96/MichaelMurphy06TIFF.jpg"
        },
        {
            "year": "1938",
            "description": "Bill Robertson, American businessman and politician (d. 2013)",
            "wikipedia": [
                {
                    "title": "Bill Robertson (Louisiana politician)",
                    "wikipedia": "https://wikipedia.org/wiki/Bill_Robertson_(Louisiana_politician)"
                }
            ],
            "url_image": "https://www.ksla.com/resizer/Sz_c0P3Z1g5HWQFV40fdnCd2m_w=/1400x0/arc-anglerfish-arc2-prod-raycom.s3.amazonaws.com/public/YZMZAHE375FZVPB4LPDZFRPRWI.jpg"
        },
        {
            "year": "1938",
            "description": "Barbara Wagner, Canadian figure skater and coach",
            "wikipedia": [
                {
                    "title": "Barbara Wagner",
                    "wikipedia": "https://wikipedia.org/wiki/Barbara_Wagner"
                }
            ],
            "url_image": "http://brasilia.memoriaeinvencao.com/wp-content/uploads/2018/03/260717-GB-Entrevista-com-Barbara-Wagner-cr%C3%A9ditoGiovanna-Bembom_Metr%C3%B3poles_edited.jpg"
        },
        {
            "year": "1939",
            "description": "Ray Gosling, English journalist, author, and activist (d. 2013)",
            "wikipedia": [
                {
                    "title": "Ray Gosling",
                    "wikipedia": "https://wikipedia.org/wiki/Ray_Gosling"
                }
            ],
            "url_image": "https://upload.wikimedia.org/wikipedia/commons/f/f6/Ryan_Gosling_in_2018.jpg"
        },
        {
            "year": "1940",
            "description": "Lance Henriksen, American actor",
            "wikipedia": [
                {
                    "title": "Lance Henriksen",
                    "wikipedia": "https://wikipedia.org/wiki/Lance_Henriksen"
                }
            ],
            "url_image": "https://media.fstatic.com/WPpBcqVue-khvrQo6s-C_COvynY=/195x289/smart/media/artists/avatar/2018/12/lance-henriksen_a5783.jpg"
        },
        {
            "year": "1940",
            "description": "Michael Lindsay-Hogg, American director and producer",
            "wikipedia": [
                {
                    "title": "Michael Lindsay-Hogg",
                    "wikipedia": "https://wikipedia.org/wiki/Michael_Lindsay-Hogg"
                }
            ],
            "url_image": "https://upload.wikimedia.org/wikipedia/commons/e/ec/Geraldine-Fitzgerald-Lindsay-Hogg-1944.jpg"
        },
        {
            "year": "1941",
            "description": "Alexander Ragulin, Russian ice hockey player (d. 2004)",
            "wikipedia": [
                {
                    "title": "Alexander Ragulin",
                    "wikipedia": "https://wikipedia.org/wiki/Alexander_Ragulin"
                }
            ],
            "url_image": "https://upload.wikimedia.org/wikipedia/commons/0/01/RUSMARKA-1754.jpg"
        },
        {
            "year": "1942",
            "description": "István Bujtor, Hungarian actor, director, producer, and screenwriter (d. 2009)",
            "wikipedia": [
                {
                    "title": "István Bujtor",
                    "wikipedia": "https://wikipedia.org/wiki/Istv%C3%A1n_Bujtor"
                }
            ],
            "url_image": "https://upload.wikimedia.org/wikipedia/en/thumb/e/e4/Istv%C3%A1n_Bujtor.jpg/220px-Istv%C3%A1n_Bujtor.jpg"
        },
        {
            "year": "1942",
            "description": "Jean Corston, Baroness Corston, English lawyer and politician",
            "wikipedia": [
                {
                    "title": "Jean Corston, Baroness Corston",
                    "wikipedia": "https://wikipedia.org/wiki/Jean_Corston,_Baroness_Corston"
                }
            ],
            "url_image": "https://static1.fiquediva.com.br/products/5/58/5/@/585--product_info_main-8.png"
        },
        {
            "year": "1942",
            "description": "Hugh Courtenay, 18th Earl of Devon, English politician (d. 2015)",
            "wikipedia": [
                {
                    "title": "Hugh Courtenay, 18th Earl of Devon",
                    "wikipedia": "https://wikipedia.org/wiki/Hugh_Courtenay,_18th_Earl_of_Devon"
                }
            ],
            "url_image": "https://upload.wikimedia.org/wikipedia/en/2/21/Hugh_Courtenay%2C_18th_Earl_of_Devon.jpg"
        },
        {
            "year": "1942",
            "description": "Tammy Wynette, American singer-songwriter and guitarist (d. 1998)",
            "wikipedia": [
                {
                    "title": "Tammy Wynette",
                    "wikipedia": "https://wikipedia.org/wiki/Tammy_Wynette"
                }
            ],
            "url_image": "https://upload.wikimedia.org/wikipedia/commons/c/cd/Tammy_Wynette.JPG"
        },
        {
            "year": "1943",
            "description": "Michael Palin, English actor and screenwriter",
            "wikipedia": [
                {
                    "title": "Michael Palin",
                    "wikipedia": "https://wikipedia.org/wiki/Michael_Palin"
                }
            ],
            "url_image": "https://upload.wikimedia.org/wikipedia/commons/7/75/Michael_Palin.jpg"
        },
        {
            "year": "1943",
            "description": "Ignacio Ramonet, Spanish journalist and author",
            "wikipedia": [
                {
                    "title": "Ignacio Ramonet",
                    "wikipedia": "https://wikipedia.org/wiki/Ignacio_Ramonet"
                }
            ],
            "url_image": "https://upload.wikimedia.org/wikipedia/commons/6/67/Ignacio_Ramonet-_GALILEE.jpg"
        },
        {
            "year": "1944",
            "description": "Bo Larsson, Swedish footballer",
            "wikipedia": [
                {
                    "title": "Bo Larsson",
                    "wikipedia": "https://wikipedia.org/wiki/Bo_Larsson"
                }
            ],
            "url_image": "https://upload.wikimedia.org/wikipedia/commons/f/ff/Bosse_Larsson_1965_%28cropped%29.jpg"
        },
        {
            "year": "1944",
            "description": "John Rhys-Davies, Welsh actor and screenwriter",
            "wikipedia": [
                {
                    "title": "John Rhys-Davies",
                    "wikipedia": "https://wikipedia.org/wiki/John_Rhys-Davies"
                }
            ],
            "url_image": "https://upload.wikimedia.org/wikipedia/commons/thumb/7/7c/%28John_Rhys-Davies%29_2018-02-11_15-35-40_ILCE-6500_DSC07150_%2831235662177%29_%28cropped%29.jpg/1200px-%28John_Rhys-Davies%29_2018-02-11_15-35-40_ILCE-6500_DSC07150_%2831235662177%29_%28cropped%29.jpg"
        },
        {
            "year": "1944",
            "description": "Roger Rees, Welsh-American actor and director (d. 2015)",
            "wikipedia": [
                {
                    "title": "Roger Rees",
                    "wikipedia": "https://wikipedia.org/wiki/Roger_Rees"
                }
            ],
            "url_image": "https://upload.wikimedia.org/wikipedia/commons/thumb/4/48/Roger_Rees.jpg/1200px-Roger_Rees.jpg"
        },
        {
            "year": "1945",
            "description": "Kurt Loder, American journalist, author, and critic",
            "wikipedia": [
                {
                    "title": "Kurt Loder",
                    "wikipedia": "https://wikipedia.org/wiki/Kurt_Loder"
                }
            ],
            "url_image": "https://upload.wikimedia.org/wikipedia/commons/f/ff/Kurt_Loder_2015.jpg"
        },
        {
            "year": "1945",
            "description": "Dianne Willcocks, English sociologist and academic",
            "wikipedia": [
                {
                    "title": "Dianne Willcocks",
                    "wikipedia": "https://wikipedia.org/wiki/Dianne_Willcocks"
                }
            ],
            "url_image": "https://i1.wp.com/www.eurashe.eu/wp-content/uploads/2014/10/Dianne_Willcoks_UK.jpg?fit=200%2C200&ssl=1"
        },
        {
            "year": "1946",
            "description": "Aydın Menderes, Turkish politician (d. 2011)",
            "wikipedia": [
                {
                    "title": "Aydın Menderes",
                    "wikipedia": "https://wikipedia.org/wiki/Ayd%C4%B1n_Menderes"
                }
            ],
            "url_image": "https://www.turkiyehavadis.com/images/haberler/2019/12/merhum-aydin-menderes-vefatinin-9-yilinda-aniliyor.jpg"
        },
        {
            "year": "1948",
            "description": "Bella van der Spiegel-Hage, Dutch cyclist",
            "wikipedia": [
                {
                    "title": "Bella van der Spiegel-Hage",
                    "wikipedia": "https://wikipedia.org/wiki/Bella_van_der_Spiegel-Hage"
                }
            ],
            "url_image": "https://upload.wikimedia.org/wikipedia/commons/thumb/2/27/Keetie_and_Bella_Hage_1968.jpg/235px-Keetie_and_Bella_Hage_1968.jpg"
        },
        {
            "year": "1948",
            "description": "Bill Ward, English drummer and songwriter",
            "wikipedia": [
                {
                    "title": "Bill Ward (musician)",
                    "wikipedia": "https://wikipedia.org/wiki/Bill_Ward_(musician)"
                }
            ],
            "url_image": "https://upload.wikimedia.org/wikipedia/commons/thumb/7/7d/Black_Sabbath_%281970%29_%28cropped%29.jpg/220px-Black_Sabbath_%281970%29_%28cropped%29.jpg"
        },
        {
            "year": "1949",
            "description": "Eppie Bleeker, Dutch speed skater",
            "wikipedia": [
                {
                    "title": "Eppie Bleeker",
                    "wikipedia": "https://wikipedia.org/wiki/Eppie_Bleeker"
                }
            ],
            "url_image": "https://upload.wikimedia.org/wikipedia/commons/9/97/Eppie_Bleeker_1974.jpg"
        },
        {
            "year": "1950",
            "description": "Rex Caldwell, American golfer",
            "wikipedia": [
                {
                    "title": "Rex Caldwell",
                    "wikipedia": "https://wikipedia.org/wiki/Rex_Caldwell"
                }
            ],
            "url_image": "https://res.cloudinary.com/pga-tour/image/upload/q_auto,t_headshots_player_l/v1/headshots_01162.png"
        },
        {
            "year": "1950",
            "description": "Maggie MacNeal, Dutch singer",
            "wikipedia": [
                {
                    "title": "Maggie MacNeal",
                    "wikipedia": "https://wikipedia.org/wiki/Maggie_MacNeal"
                }
            ],
            "url_image": "https://upload.wikimedia.org/wikipedia/commons/d/de/Maggie_MacNeal.png"
        },
        {
            "year": "1951",
            "description": "Rudolf Finsterer, German rugby player and coach",
            "wikipedia": [
                {
                    "title": "Rudolf Finsterer",
                    "wikipedia": "https://wikipedia.org/wiki/Rudolf_Finsterer"
                }
            ],
            "url_image": "https://alchetron.com/cdn/rudolf-finsterer-b08472d3-76ee-4cb3-a12c-a64a5980dc1-resize-750.jpeg"
        },
        {
            "year": "1951",
            "description": "Toomas Vilosius, Estonian physician and politician, 2nd Minister of Social Affairs of Estonia",
            "wikipedia": [
                {
                    "title": "Toomas Vilosius",
                    "wikipedia": "https://wikipedia.org/wiki/Toomas_Vilosius"
                },
                {
                    "title": "Minister of Social Affairs of Estonia",
                    "wikipedia": "https://wikipedia.org/wiki/Minister_of_Social_Affairs_of_Estonia"
                }
            ],
            "url_image": "https://www.regionaalhaigla.ee/sites/default/files/documents/sisu_166_thumb.jpg"
        },
        {
            "year": "1952",
            "description": "Jorge Llopart, Spanish race walker",
            "wikipedia": [
                {
                    "title": "Jorge Llopart",
                    "wikipedia": "https://wikipedia.org/wiki/Jorge_Llopart"
                }
            ],
            "url_image": "https://upload.wikimedia.org/wikipedia/commons/3/38/Jorge_Llopart_1980.jpg"
        },
        {
            "year": "1952",
            "description": "Willem Witteveen, Dutch scholar and politician (d. 2014)",
            "wikipedia": [
                {
                    "title": "Willem Witteveen",
                    "wikipedia": "https://wikipedia.org/wiki/Willem_Witteveen"
                }
            ],
            "url_image": "https://upload.wikimedia.org/wikipedia/commons/thumb/e/ef/Willem_Witteveen_%2812082628245%29_%282%29.jpg/200px-Willem_Witteveen_%2812082628245%29_%282%29.jpg"
        },
        {
            "year": "1955",
            "description": "Jon Butcher, American singer-songwriter, guitarist, and freelance multimedia producer",
            "wikipedia": [
                {
                    "title": "Jon Butcher",
                    "wikipedia": "https://wikipedia.org/wiki/Jon_Butcher"
                }
            ],
            "url_image": "https://storyblok-cdn.mindvalley.com/f/60579/600x280/7f21d2ddde/lbo_lp_signup_btm_m.jpg?trans?quality=75&dpr=2.625&width=412"
        },
        {
            "year": "1956",
            "description": "Steve Scott, American runner and coach",
            "wikipedia": [
                {
                    "title": "Steve Scott (athlete)",
                    "wikipedia": "https://wikipedia.org/wiki/Steve_Scott_(athlete)"
                }
            ],
            "url_image": "https://bringbackthemile.com/images/sized/images/ugc/uploads/about/Steve_Scott_Sub-4a-0x270.JPG"
        },
        {
            "year": "1957",
            "description": "Richard E. Grant, Swazi-English actor, director, and screenwriter",
            "wikipedia": [
                {
                    "title": "Richard E. Grant",
                    "wikipedia": "https://wikipedia.org/wiki/Richard_E._Grant"
                }
            ],
            "url_image": "https://upload.wikimedia.org/wikipedia/commons/2/29/Richard_E._Grant_2018.jpg"
        },
        {
            "year": "1957",
            "description": "Peter Howitt, English actor, director, and screenwriter",
            "wikipedia": [
                {
                    "title": "Peter Howitt",
                    "wikipedia": "https://wikipedia.org/wiki/Peter_Howitt"
                }
            ],
            "url_image": "https://images.mubicdn.net/images/cast_member/41863/cache-76698-1371835667/image-w856.jpg?size=800x"
        },
        {
            "year": "1957",
            "description": "Aad van Mil, Dutch water polo player",
            "wikipedia": [
                {
                    "title": "Aad van Mil",
                    "wikipedia": "https://wikipedia.org/wiki/Aad_van_Mil"
                }
            ],
            "url_image": "https://upload.wikimedia.org/wikipedia/commons/thumb/d/d4/Aad_Van_Mil_2020.jpeg/360px-Aad_Van_Mil_2020.jpeg"
        },
        {
            "year": "1958",
            "description": "Ron Arad, Israeli colonel and pilot (d. 1986)",
            "wikipedia": [
                {
                    "title": "Ron Arad (pilot)",
                    "wikipedia": "https://wikipedia.org/wiki/Ron_Arad_(pilot)"
                }
            ],
            "url_image": "https://upload.wikimedia.org/wikipedia/en/4/4a/Ron_Arad_2.jpg"
        },
        {
            "year": "1958",
            "description": "Robert DiPierdomenico, Australian footballer and sportscaster",
            "wikipedia": [
                {
                    "title": "Robert DiPierdomenico",
                    "wikipedia": "https://wikipedia.org/wiki/Robert_DiPierdomenico"
                }
            ],
            "url_image": "https://upload.wikimedia.org/wikipedia/commons/thumb/2/25/Robert_dipierdomenico.jpg/220px-Robert_dipierdomenico.jpg"
        },
        {
            "year": "1958",
            "description": "Vanessa Downing, Australian actress",
            "wikipedia": [
                {
                    "title": "Vanessa Downing",
                    "wikipedia": "https://wikipedia.org/wiki/Vanessa_Downing"
                }
            ],
            "url_image": "https://mollisonkeightley.com/wp-content/uploads/2016/08/Vanessa-Downing.jpg"
        },
        {
            "year": "1958",
            "description": "Jack Wishna, American businessman, co-founded Rockcityclub (d. 2012)",
            "wikipedia": [
                {
                    "title": "Jack Wishna",
                    "wikipedia": "https://wikipedia.org/wiki/Jack_Wishna"
                },
                {
                    "title": "Rockcityclub",
                    "wikipedia": "https://wikipedia.org/wiki/Rockcityclub"
                }
            ],
            "url_image": "https://pbs.twimg.com/profile_images/463152505/VegasMagazine2_400x400.jpg"
        },
        {
            "year": "1959",
            "description": "Bobby Ellsworth, American singer and bass player",
            "wikipedia": [
                {
                    "title": "Bobby Ellsworth",
                    "wikipedia": "https://wikipedia.org/wiki/Bobby_Ellsworth"
                }
            ],
            "url_image": "https://upload.wikimedia.org/wikipedia/commons/0/03/Overkill_-_Jalometalli_2008_-_02.JPG"
        },
        {
            "year": "1959",
            "description": "Ian McCulloch, English singer-songwriter and guitarist",
            "wikipedia": [
                {
                    "title": "Ian McCulloch (singer)",
                    "wikipedia": "https://wikipedia.org/wiki/Ian_McCulloch_(singer)"
                }
            ],
            "url_image": "https://upload.wikimedia.org/wikipedia/commons/1/12/Ian_McCulloch2.jpg"
        },
        {
            "year": "1959",
            "description": "Steve Stevens, American guitarist and songwriter",
            "wikipedia": [
                {
                    "title": "Steve Stevens",
                    "wikipedia": "https://wikipedia.org/wiki/Steve_Stevens"
                }
            ],
            "url_image": "https://upload.wikimedia.org/wikipedia/commons/thumb/c/c1/SteveStevens.JPG/1200px-SteveStevens.JPG"
        },
        {
            "year": "1959",
            "description": "Brian Williams, American journalist",
            "wikipedia": [
                {
                    "title": "Brian Williams",
                    "wikipedia": "https://wikipedia.org/wiki/Brian_Williams"
                }
            ],
            "url_image": "https://upload.wikimedia.org/wikipedia/commons/a/a3/Brian_Williams_2011_Shankbone.JPG"
        },
        {
            "year": "1960",
            "description": "Doug Hawkins, Australian footballer and sportscaster",
            "wikipedia": [
                {
                    "title": "Doug Hawkins",
                    "wikipedia": "https://wikipedia.org/wiki/Doug_Hawkins"
                }
            ],
            "url_image": "https://upload.wikimedia.org/wikipedia/commons/c/cd/Doug_Hawkins_Statue_%2848742999558%29.jpg"
        },
        {
            "year": "1961",
            "description": "Marg Downey, Australian actress",
            "wikipedia": [
                {
                    "title": "Marg Downey",
                    "wikipedia": "https://wikipedia.org/wiki/Marg_Downey"
                }
            ],
            "url_image": "https://creativerep.com.au/wp-content/uploads/2017/03/DOWNEY-Marg-1-Copy.jpg"
        },
        {
            "year": "1961",
            "description": "Hiroshi Hase, Japanese wrestler and politician",
            "wikipedia": [
                {
                    "title": "Hiroshi Hase",
                    "wikipedia": "https://wikipedia.org/wiki/Hiroshi_Hase"
                }
            ],
            "url_image": "https://static.wikia.nocookie.net/puroresusystem/images/5/5f/Hiroshi_Hase123.jpg/revision/latest/top-crop/width/360/height/450?cb=20160814100436"
        },
        {
            "year": "1961",
            "description": "Rob Williams, American basketball player (d. 2014)",
            "wikipedia": [
                {
                    "title": "Rob Williams (basketball)",
                    "wikipedia": "https://wikipedia.org/wiki/Rob_Williams_(basketball)"
                }
            ],
            "url_image": "https://a.espncdn.com/combiner/i?img=/i/headshots/nba/players/full/4066211.png"
        },
        {
            "year": "1962",
            "description": "Kaoru Wada, Japanese composer and conductor",
            "wikipedia": [
                {
                    "title": "Kaoru Wada",
                    "wikipedia": "https://wikipedia.org/wiki/Kaoru_Wada"
                }
            ],
            "url_image": "https://cdn.myanimelist.net/images/voiceactors/1/49350.jpg"
        },
        {
            "year": "1963",
            "description": "James LaBrie, Canadian singer-songwriter",
            "wikipedia": [
                {
                    "title": "James LaBrie",
                    "wikipedia": "https://wikipedia.org/wiki/James_LaBrie"
                }
            ],
            "url_image": "https://upload.wikimedia.org/wikipedia/commons/d/d8/James_LaBrie_-_02.jpg"
        },
        {
            "year": "1963",
            "description": "Simon Rimmer, English chef and author",
            "wikipedia": [
                {
                    "title": "Simon Rimmer",
                    "wikipedia": "https://wikipedia.org/wiki/Simon_Rimmer"
                }
            ],
            "url_image": "https://pagestudio.s3.amazonaws.com/simon-rimmer/b7874e38d0add8734c1f35a8f50ee89c.jpg"
        },
        {
            "year": "1963",
            "description": "Scott Westerfeld, American author and composer",
            "wikipedia": [
                {
                    "title": "Scott Westerfeld",
                    "wikipedia": "https://wikipedia.org/wiki/Scott_Westerfeld"
                }
            ],
            "url_image": "https://upload.wikimedia.org/wikipedia/commons/thumb/a/a0/Scott_Westerfeld.jpg/1200px-Scott_Westerfeld.jpg"
        },
        {
            "year": "1964",
            "description": "Jean-François Copé, French politician, French Minister of Budget",
            "wikipedia": [
                {
                    "title": "Jean-François Copé",
                    "wikipedia": "https://wikipedia.org/wiki/Jean-Fran%C3%A7ois_Cop%C3%A9"
                }
            ],
            "url_image": "https://upload.wikimedia.org/wikipedia/commons/b/ba/Jean-Fran%C3%A7ois_Cop%C3%A9%2C_D%C3%A9put%C3%A9-maire_de_Meaux_2015_%28cropped%29.jpg"
        },
        {
            "year": "1964",
            "description": "Heike Henkel, German high jumper",
            "wikipedia": [
                {
                    "title": "Heike Henkel",
                    "wikipedia": "https://wikipedia.org/wiki/Heike_Henkel"
                }
            ],
            "url_image": "https://upload.wikimedia.org/wikipedia/commons/thumb/3/31/Heike_Henkel_cropped.jpg/190px-Heike_Henkel_cropped.jpg"
        },
        {
            "year": "1964",
            "description": "Don Payne, American screenwriter and producer (d. 2013)",
            "wikipedia": [
                {
                    "title": "Don Payne (writer)",
                    "wikipedia": "https://wikipedia.org/wiki/Don_Payne_(writer)"
                }
            ],
            "url_image": "https://upload.wikimedia.org/wikipedia/commons/b/ba/DonPayneJuly08.jpg"
        },
        {
            "year": "1964",
            "description": "Minami Takayama, Japanese voice actress and singer",
            "wikipedia": [
                {
                    "title": "Minami Takayama",
                    "wikipedia": "https://wikipedia.org/wiki/Minami_Takayama"
                }
            ],
            "url_image": "https://cdn.myanimelist.net/images/voiceactors/1/42419.jpg"
        },
        {
            "year": "1965",
            "description": "Glenn Seton, Australian race car driver",
            "wikipedia": [
                {
                    "title": "Glenn Seton",
                    "wikipedia": "https://wikipedia.org/wiki/Glenn_Seton"
                }
            ],
            "url_image": "https://upload.wikimedia.org/wikipedia/commons/thumb/4/45/Glenn_Seton_1997_EL_Falcon_Muscle_Car_Masters_2011.JPG/220px-Glenn_Seton_1997_EL_Falcon_Muscle_Car_Masters_2011.JPG"
        },
        {
            "year": "1966",
            "description": "Shawn Drover, Canadian drummer",
            "wikipedia": [
                {
                    "title": "Shawn Drover",
                    "wikipedia": "https://wikipedia.org/wiki/Shawn_Drover"
                }
            ],
            "url_image": "https://upload.wikimedia.org/wikipedia/commons/thumb/6/60/Megadeth_live_in_Bucharest%2C_June_15th%2C_2005.jpg/250px-Megadeth_live_in_Bucharest%2C_June_15th%2C_2005.jpg"
        },
        {
            "year": "1966",
            "description": "Sergei Stanishev, Bulgarian politician, 46th Prime Minister of Bulgaria",
            "wikipedia": [
                {
                    "title": "Sergei Stanishev",
                    "wikipedia": "https://wikipedia.org/wiki/Sergei_Stanishev"
                },
                {
                    "title": "Prime Minister of Bulgaria",
                    "wikipedia": "https://wikipedia.org/wiki/Prime_Minister_of_Bulgaria"
                }
            ],
            "url_image": "https://upload.wikimedia.org/wikipedia/commons/8/8e/Sergey_Stanishev_2009_elections_diff_crop.jpg"
        },
        {
            "year": "1966",
            "description": "Josh Weinstein, American screenwriter and producer",
            "wikipedia": [
                {
                    "title": "Josh Weinstein",
                    "wikipedia": "https://wikipedia.org/wiki/Josh_Weinstein"
                }
            ],
            "url_image": "https://upload.wikimedia.org/wikipedia/commons/c/c0/Josh_Weinstein_-_Salford_Media_Festival_2013-2-cropped.jpg"
        },
        {
            "year": "1967",
            "description": "Adam Hughes, American author and illustrator",
            "wikipedia": [
                {
                    "title": "Adam Hughes",
                    "wikipedia": "https://wikipedia.org/wiki/Adam_Hughes"
                }
            ],
            "url_image": "https://images-na.ssl-images-amazon.com/images/I/71Ck5Jm4l9L.jpg"
        },
        {
            "year": "1967",
            "description": "Alexis Sinduhije, Burundian journalist and politician",
            "wikipedia": [
                {
                    "title": "Alexis Sinduhije",
                    "wikipedia": "https://wikipedia.org/wiki/Alexis_Sinduhije"
                }
            ],
            "url_image": "http://img.timeinc.net/time/2008/time_100_2008/alexis_sinduhije.jpg"
        },
        {
            "year": "1969",
            "description": "Pieter Muller, South African rugby player",
            "wikipedia": [
                {
                    "title": "Pieter Muller",
                    "wikipedia": "https://wikipedia.org/wiki/Pieter_Muller"
                }
            ],
            "url_image": "https://media.gettyimages.com/photos/pieter-muller-south-africa-picture-id650812900?s=612x612"
        },
        {
            "year": "1970",
            "description": "Kyan Douglas, American television host and author",
            "wikipedia": [
                {
                    "title": "Kyan Douglas",
                    "wikipedia": "https://wikipedia.org/wiki/Kyan_Douglas"
                }
            ],
            "url_image": "https://upload.wikimedia.org/wikipedia/commons/c/ca/Kyandouglas.jpg"
        },
        {
            "year": "1970",
            "description": "LaPhonso Ellis, American basketball player",
            "wikipedia": [
                {
                    "title": "LaPhonso Ellis",
                    "wikipedia": "https://wikipedia.org/wiki/LaPhonso_Ellis"
                }
            ],
            "url_image": "https://cdn.vox-cdn.com/thumbor/mux8nILYQSkCB2tnBTVB4CBiFbc=/0x219:732x707/1400x1400/filters:focal(0x219:732x707):format(jpeg)/cdn.vox-cdn.com/uploads/chorus_image/image/17664069/56704417.0.jpg"
        },
        {
            "year": "1970",
            "description": "Todd Newton, American Game Show Host",
            "wikipedia": [
                {
                    "title": "Todd Newton",
                    "wikipedia": "https://wikipedia.org/wiki/Todd_Newton"
                }
            ],
            "url_image": "https://upload.wikimedia.org/wikipedia/commons/9/95/Television_host_Todd_Newton.jpg"
        },
        {
            "year": "1971",
            "description": "Harold Miner, American basketball player",
            "wikipedia": [
                {
                    "title": "Harold Miner",
                    "wikipedia": "https://wikipedia.org/wiki/Harold_Miner"
                }
            ],
            "url_image": "https://upload.wikimedia.org/wikipedia/commons/3/31/Harold_Miner.jpg"
        },
        {
            "year": "1971",
            "description": "Mike Redmond, American baseball player and manager",
            "wikipedia": [
                {
                    "title": "Mike Redmond",
                    "wikipedia": "https://wikipedia.org/wiki/Mike_Redmond"
                }
            ],
            "url_image": "https://upload.wikimedia.org/wikipedia/commons/a/a6/Mike_Redmond.jpg"
        },
        {
            "year": "1972",
            "description": "James Cracknell, English rower",
            "wikipedia": [
                {
                    "title": "James Cracknell",
                    "wikipedia": "https://wikipedia.org/wiki/James_Cracknell"
                }
            ],
            "url_image": "https://i.guim.co.uk/img/media/56623465912bb8e1affbbb8af9606f59e0046472/0_170_5472_3283/master/5472.jpg?width=1200&height=1200&quality=85&auto=format&fit=crop&s=98a41288cba26e52e7c836288b83e20f"
        },
        {
            "year": "1972",
            "description": "Žigmund Pálffy, Slovakian ice hockey player",
            "wikipedia": [
                {
                    "title": "Žigmund Pálffy",
                    "wikipedia": "https://wikipedia.org/wiki/%C5%BDigmund_P%C3%A1lffy"
                }
            ],
            "url_image": "https://upload.wikimedia.org/wikipedia/commons/b/b0/ZPalffy.png"
        },
        {
            "year": "1972",
            "description": "Mikael Renberg, Swedish ice hockey player",
            "wikipedia": [
                {
                    "title": "Mikael Renberg",
                    "wikipedia": "https://wikipedia.org/wiki/Mikael_Renberg"
                }
            ],
            "url_image": "https://www.hockeydb.com/ihdb/photos/mikael-renberg-1996-53.jpg"
        },
        {
            "year": "1975",
            "description": "Meb Keflezighi, American runner",
            "wikipedia": [
                {
                    "title": "Meb Keflezighi",
                    "wikipedia": "https://wikipedia.org/wiki/Meb_Keflezighi"
                }
            ],
            "url_image": "https://upload.wikimedia.org/wikipedia/commons/e/e1/Meb_Keflezighi_2009_London_Marathon-2.jpg"
        },
        {
            "year": "1976",
            "description": "Dieter Brummer, Australian actor",
            "wikipedia": [
                {
                    "title": "Dieter Brummer",
                    "wikipedia": "https://wikipedia.org/wiki/Dieter_Brummer"
                }
            ],
            "url_image": "https://upload.wikimedia.org/wikipedia/commons/6/66/Dieter_Brummer_2011_%28cropped%29.jpg"
        },
        {
            "year": "1976",
            "description": "Jean-François Dumoulin, Canadian race car driver",
            "wikipedia": [
                {
                    "title": "Jean-François Dumoulin",
                    "wikipedia": "https://wikipedia.org/wiki/Jean-Fran%C3%A7ois_Dumoulin"
                }
            ],
            "url_image": "https://www.dumoulincompetition.com/upload/site_web_2020/jf/jf_dumoulin_6599_-_credit_christian_auger.jpg"
        },
        {
            "year": "1976",
            "description": "Anastasios Pantos, Greek footballer",
            "wikipedia": [
                {
                    "title": "Anastasios Pantos",
                    "wikipedia": "https://wikipedia.org/wiki/Anastasios_Pantos"
                }
            ],
            "url_image": "https://upload.wikimedia.org/wikipedia/commons/9/9b/Pantosanastasios.JPG"
        },
        {
            "year": "1976",
            "description": "Juan Pablo Sorín, Argentinian footballer and sportscaster",
            "wikipedia": [
                {
                    "title": "Juan Pablo Sorín",
                    "wikipedia": "https://wikipedia.org/wiki/Juan_Pablo_Sor%C3%ADn"
                }
            ],
            "url_image": "https://lookaside.fbsbx.com/lookaside/crawler/media/?media_id=370305773070813"
        },
        {
            "year": "1976",
            "description": "Sage Stallone, American actor (d. 2012)",
            "wikipedia": [
                {
                    "title": "Sage Stallone",
                    "wikipedia": "https://wikipedia.org/wiki/Sage_Stallone"
                }
            ],
            "url_image": "https://1.bp.blogspot.com/-hXsN7boRFU0/XM83VLWw2zI/AAAAAAAAJ7Y/81qx7T6u37IyHfXT8DWbfrfB97C9ah40gCLcBGAs/s1600/SAGE%2BSTALLONE.jpg"
        },
        {
            "year": "1978",
            "description": "Morgan Pehme, American director, producer, and screenwriter",
            "wikipedia": [
                {
                    "title": "Morgan Pehme",
                    "wikipedia": "https://wikipedia.org/wiki/Morgan_Pehme"
                }
            ],
            "url_image": "https://images.mubicdn.net/images/cast_member/392521/cache-511309-1581142327/image-w856.jpg?size=800x"
        },
        {
            "year": "1980",
            "description": "Yossi Benayoun, Israeli footballer",
            "wikipedia": [
                {
                    "title": "Yossi Benayoun",
                    "wikipedia": "https://wikipedia.org/wiki/Yossi_Benayoun"
                }
            ],
            "url_image": "https://upload.wikimedia.org/wikipedia/commons/7/79/Benayoun_Haifa_%282a%29.jpg"
        },
        {
            "year": "1980",
            "description": "Hank Green, American entrepreneur, educator, and vlogger",
            "wikipedia": [
                {
                    "title": "Hank Green",
                    "wikipedia": "https://wikipedia.org/wiki/Hank_Green"
                }
            ],
            "url_image": "https://upload.wikimedia.org/wikipedia/commons/7/7a/Hank_Green_by_Gage_Skidmore.jpg"
        },
        {
            "year": "1980",
            "description": "DerMarr Johnson, American basketball player",
            "wikipedia": [
                {
                    "title": "DerMarr Johnson",
                    "wikipedia": "https://wikipedia.org/wiki/DerMarr_Johnson"
                }
            ],
            "url_image": "https://cdn.theathletic.com/app/uploads/2019/05/03005836/JohnsonDerMarr.jpg"
        },
        {
            "year": "1981",
            "description": "Craig David, English singer-songwriter, musician and producer",
            "wikipedia": [
                {
                    "title": "Craig David",
                    "wikipedia": "https://wikipedia.org/wiki/Craig_David"
                }
            ],
            "url_image": "https://i.pinimg.com/originals/25/f9/4b/25f94bdd195dffa107410f9b433c8004.jpg"
        },
        {
            "year": "1982",
            "description": "Ferrie Bodde, Dutch footballer",
            "wikipedia": [
                {
                    "title": "Ferrie Bodde",
                    "wikipedia": "https://wikipedia.org/wiki/Ferrie_Bodde"
                }
            ],
            "url_image": "https://i2-prod.walesonline.co.uk/incoming/article13171966.ece/ALTERNATES/s615/bodmain1.jpg"
        },
        {
            "year": "1982",
            "description": "Wouter D'Haene, Belgian sprinter",
            "wikipedia": [
                {
                    "title": "Wouter D'Haene",
                    "wikipedia": "https://wikipedia.org/wiki/Wouter_D%27Haene"
                }
            ],
            "url_image": "https://images0.persgroep.net/rcs/6HLlnUXf-IR_2fvXo2p7uao9qLM/diocontent/59555013/_crop/1/50/899/508/_fitwidth/763?appId=93a17a8fd81db0de025c8abd1cca1279&quality=0.8"
        },
        {
            "year": "1982",
            "description": "Randall Gay, American football player",
            "wikipedia": [
                {
                    "title": "Randall Gay",
                    "wikipedia": "https://wikipedia.org/wiki/Randall_Gay"
                }
            ],
            "url_image": "https://upload.wikimedia.org/wikipedia/commons/thumb/6/6c/Randall_Gay_in_2011.jpg/1200px-Randall_Gay_in_2011.jpg"
        },
        {
            "year": "1982",
            "description": "Corey Parker, Australian rugby league footballer",
            "wikipedia": [
                {
                    "title": "Corey Parker (rugby league)",
                    "wikipedia": "https://wikipedia.org/wiki/Corey_Parker_(rugby_league)"
                }
            ],
            "url_image": "https://upload.wikimedia.org/wikipedia/commons/thumb/c/c6/Corey_Parker_PM_XIII.jpg/180px-Corey_Parker_PM_XIII.jpg"
        },
        {
            "year": "1983",
            "description": "James Anyon, English cricketer",
            "wikipedia": [
                {
                    "title": "James Anyon",
                    "wikipedia": "https://wikipedia.org/wiki/James_Anyon"
                }
            ],
            "url_image": "https://ichef.bbci.co.uk/news/640/cpsprodpb/0508/production/_89088210_jamesanyon.jpg"
        },
        {
            "year": "1983",
            "description": "Henry Cavill, English actor",
            "wikipedia": [
                {
                    "title": "Henry Cavill",
                    "wikipedia": "https://wikipedia.org/wiki/Henry_Cavill"
                }
            ],
            "url_image": "https://wikipop.com.br/wp-content/uploads/2020/11/henry-cavill-800x670.jpg"
        },
        {
            "year": "1983",
            "description": "Mabel Gay, Cuban triple jumper",
            "wikipedia": [
                {
                    "title": "Mabel Gay",
                    "wikipedia": "https://wikipedia.org/wiki/Mabel_Gay"
                }
            ],
            "url_image": "https://upload.wikimedia.org/wikipedia/commons/0/09/Deporcuba_entrevista_Mabel_Gay_%28cropped%29.jpg"
        },
        {
            "year": "1983",
            "description": "Annie Villeneuve, Canadian singer-songwriter",
            "wikipedia": [
                {
                    "title": "Annie Villeneuve",
                    "wikipedia": "https://wikipedia.org/wiki/Annie_Villeneuve"
                }
            ],
            "url_image": "https://studiosol-a.akamaihd.net/uploadfile/letras/fotos/4/0/4/a/404a8dfdd3ea27a60e2c3c7b86cff823.jpg"
        },
        {
            "year": "1983",
            "description": "Scott Ware, American football player",
            "wikipedia": [
                {
                    "title": "Scott Ware",
                    "wikipedia": "https://wikipedia.org/wiki/Scott_Ware"
                }
            ],
            "url_image": "https://profilemagazine.com/wp-content/uploads/2018/11/Scott-Ware_MirrorCache_thumbnail.jpg"
        },
        {
            "year": "1984",
            "description": "Wade MacNeil, Canadian singer-songwriter and guitarist",
            "wikipedia": [
                {
                    "title": "Wade MacNeil",
                    "wikipedia": "https://wikipedia.org/wiki/Wade_MacNeil"
                }
            ],
            "url_image": "https://www.tenhomaisdiscosqueamigos.com/wp-content/uploads/2020/04/wade-macneil-696x590.jpg"
        },
        {
            "year": "1984",
            "description": "Christian Valdez, Mexican footballer",
            "wikipedia": [
                {
                    "title": "Christian Valdez",
                    "wikipedia": "https://wikipedia.org/wiki/Christian_Valdez"
                }
            ],
            "url_image": "https://img.a.transfermarkt.technology/portrait/header/53064-1441288198.jpg?lm=1"
        },
        {
            "year": "1985",
            "description": "Shoko Nakagawa, Japanese actress and singer",
            "wikipedia": [
                {
                    "title": "Shoko Nakagawa",
                    "wikipedia": "https://wikipedia.org/wiki/Shoko_Nakagawa"
                }
            ],
            "url_image": "https://upload.wikimedia.org/wikipedia/commons/8/8e/Rogue_One-_A_Star_Wars_Story_Japan_Premiere_Red_Carpet-_Nakagawa_Shoko_%2834988933823%29.jpg"
        },
        {
            "year": "1985",
            "description": "Emanuele Giaccherini, Italian footballer",
            "wikipedia": [
                {
                    "title": "Emanuele Giaccherini",
                    "wikipedia": "https://wikipedia.org/wiki/Emanuele_Giaccherini"
                }
            ],
            "url_image": "https://tmssl.akamaized.net/images/foto/normal/emanuele-giaccherini-1468502650-5669.jpg?lm=1483606094"
        },
        {
            "year": "1985",
            "description": "Tsepo Masilela, South African footballer",
            "wikipedia": [
                {
                    "title": "Tsepo Masilela",
                    "wikipedia": "https://wikipedia.org/wiki/Tsepo_Masilela"
                }
            ],
            "url_image": "https://img.a.transfermarkt.technology/portrait/header/s_63287_1064_2010_1.jpg?lm=1"
        },
        {
            "year": "1985",
            "description": "Marcos Rogério Oliveira Duarte, Brazilian footballer",
            "wikipedia": [
                {
                    "title": "Marcos Rogério Oliveira Duarte",
                    "wikipedia": "https://wikipedia.org/wiki/Marcos_Rog%C3%A9rio_Oliveira_Duarte"
                }
            ],
            "url_image": "https://www.gremiopedia.com/images/b/ba/Marcos_Rog%C3%A9rio_Oliveira_Duarte.jpg"
        },
        {
            "year": "1985",
            "description": "Terrence Wheatley, American football player",
            "wikipedia": [
                {
                    "title": "Terrence Wheatley",
                    "wikipedia": "https://wikipedia.org/wiki/Terrence_Wheatley"
                }
            ],
            "url_image": "https://i0.wp.com/timothyfeatures.com/wp-content/uploads/2020/07/NewEnglandPatriotsTrainingCamp7CNOiaBEyGox.jpg?resize=827%2C1024&ssl=1"
        },
        {
            "year": "1987",
            "description": "Graham Dorrans, Scottish footballer",
            "wikipedia": [
                {
                    "title": "Graham Dorrans",
                    "wikipedia": "https://wikipedia.org/wiki/Graham_Dorrans"
                }
            ],
            "url_image": "https://upload.wikimedia.org/wikipedia/commons/1/1e/Graham_Dorrans.jpg"
        },
        {
            "year": "1988",
            "description": "Adele, English singer-songwriter",
            "wikipedia": [
                {
                    "title": "Adele",
                    "wikipedia": "https://wikipedia.org/wiki/Adele"
                }
            ],
            "url_image": "https://upload.wikimedia.org/wikipedia/commons/7/7c/Adele_2016.jpg"
        },
        {
            "year": "1988",
            "description": "Mervyn Westfield, English cricketer",
            "wikipedia": [
                {
                    "title": "Mervyn Westfield",
                    "wikipedia": "https://wikipedia.org/wiki/Mervyn_Westfield"
                }
            ],
            "url_image": "https://i2-prod.mirror.co.uk/incoming/article688923.ece/ALTERNATES/s1200c/Former%20Essex%20County%20cricketer%20Mervyn%20Westfield"
        },
        {
            "year": "1989",
            "description": "Chris Brown, American singer-songwriter, dancer, and actor",
            "wikipedia": [
                {
                    "title": "Chris Brown",
                    "wikipedia": "https://wikipedia.org/wiki/Chris_Brown"
                }
            ],
            "url_image": "https://static1.purepeople.com.br/articles/0/19/75/0/@/181778-chris-brown-624x600-2.jpg"
        },
        {
            "year": "1991",
            "description": "Xenofon Fetsis, Greek footballer",
            "wikipedia": [
                {
                    "title": "Xenofon Fetsis",
                    "wikipedia": "https://wikipedia.org/wiki/Xenofon_Fetsis"
                }
            ],
            "url_image": "https://www.ogol.com.br/img/jogadores/66/131166_med_xenofon_fetsis.jpg"
        },
        {
            "year": "1991",
            "description": "Raúl Jiménez, Mexican footballer",
            "wikipedia": [
                {
                    "title": "Raúl Jiménez",
                    "wikipedia": "https://wikipedia.org/wiki/Ra%C3%BAl_Jim%C3%A9nez"
                }
            ],
            "url_image": "https://s2.glbimg.com/8YftPt5wXbLQbJoFjGHD9kEkBMM=/0x0:4960x3302/984x0/smart/filters:strip_icc()/i.s3.glbimg.com/v1/AUTH_bc8228b6673f488aa253bbcb03c80ec5/internal_photos/bs/2020/h/d/SGy4BBQX2N6EReIUadtA/2020-11-29t192454z-2107318820-up1egbt1hxi1j-rtrmadp-3-soccer-england-ars-wlv-report.jpg"
        },
        {
            "year": "1992",
            "description": "Loïck Landre, French footballer",
            "wikipedia": [
                {
                    "title": "Loïck Landre",
                    "wikipedia": "https://wikipedia.org/wiki/Lo%C3%AFck_Landre"
                }
            ],
            "url_image": "https://img.a.transfermarkt.technology/portrait/header/164912-1600520494.jpg?lm=1"
        },
        {
            "year": "1996",
            "description": "Isaac Heeney, Australian footballer",
            "wikipedia": [
                {
                    "title": "Isaac Heeney",
                    "wikipedia": "https://wikipedia.org/wiki/Isaac_Heeney"
                }
            ],
            "url_image": "https://upload.wikimedia.org/wikipedia/commons/f/f7/Isaac_Heeney_2017.1.jpg"
        },
        {
            "year": "1999",
            "description": "Nathan Chen, American figure skater",
            "wikipedia": [
                {
                    "title": "Nathan Chen",
                    "wikipedia": "https://wikipedia.org/wiki/Nathan_Chen"
                }
            ],
            "url_image": "https://upload.wikimedia.org/wikipedia/commons/5/54/Nathan_Chen_at_the_2018_Internationaux_de_France_-_Awarding_ceremony.jpg"
        }
    ]
}